ga4qc/callback/__init__.py
ga4qc/callback/handle_best_circuit.py
ga4qc/callback/handle_stats.py
ga4qc/callback/handle_unique_circuit_count.py
ga4qc/callback/interface.py
ga4qc/circuit/__init__.py
ga4qc/circuit/circuit.py
ga4qc/circuit/gates/GATE_SETS.py
ga4qc/circuit/gates/__init__.py
ga4qc/circuit/gates/controlled.py
ga4qc/circuit/gates/double_controlled.py
ga4qc/circuit/gates/interfaces.py
ga4qc/circuit/gates/oracle.py
ga4qc/circuit/gates/single_qubit.py
ga4qc/circuit/gates/swap.py
ga4qc/circuit/utils.py
ga4qc/crossover/__init__.py
ga4qc/crossover/interface.py
ga4qc/crossover/one_point.py
ga4qc/ga/__init__.py
ga4qc/ga/ga.py
ga4qc/mutation/__init__.py
ga4qc/mutation/interface.py
ga4qc/mutation/parameter_change.py
ga4qc/mutation/random_gate.py
ga4qc/params.py
ga4qc/processors/__init__.py
ga4qc/processors/fitness/__init__.py
ga4qc/processors/fitness/absolute_unitary_distance.py
ga4qc/processors/fitness/gate_count.py
ga4qc/processors/fitness/interface.py
ga4qc/processors/fitness/jensen_shannon.py
ga4qc/processors/fitness/spector.py
ga4qc/processors/fitness/weighted_sum.py
ga4qc/processors/fitness/williams_ranking.py
ga4qc/processors/interface.py
ga4qc/processors/numerical_optimizer.py
ga4qc/processors/remove_duplicates.py
ga4qc/processors/simulator/__init__.py
ga4qc/processors/simulator/interface.py
ga4qc/processors/simulator/quasim_simulator.py
ga4qc/seeder/__init__.py
ga4qc/seeder/interface.py
ga4qc/seeder/random_seeder.py
ga4qc/selection/__init__.py
ga4qc/selection/best.py
ga4qc/selection/interface.py
ga4qc/selection/nsga2.py
ga4qc/selection/roulette.py
ga4qc/selection/tournament.py
ga4qc-0.4.0.dist-info/METADATA
ga4qc-0.4.0.dist-info/WHEEL
ga4qc-0.4.0.dist-info/RECORD
